{
  "moveConflictResolutionStrategy": 0,
  "unitTypes": [
    {
      "ID": 0,
      "name": "Resource",
      "cost": 1,
      "produceTime": 10,
      "hp": 1,
      "minDamage": 1,
      "maxDamage": 1,
      "attackRange": 1,
      "attackTime": 10,
      "moveTime": 10,
      "sightRadius": 0,
      "harvestTime": 10,
      "returnTime": 10,
      "harvestAmount": 1,
      "isResource": true,
      "isStockpile": false,
      "canHarvest": false,
      "canMove": false,
      "canAttack": false,
      "produces": [],
      "producedBy": []
    },
    {
      "ID": 3,
      "name": "Worker",
      "cost": 8,
      "produceTime": 2,
      "hp": 2,
      "minDamage": 1,
      "maxDamage": 2,
      "attackRange": 2,
      "attackTime": 1,
      "moveTime": 3,
      "sightRadius": 5,
      "harvestTime": 1,
      "returnTime": 1,
      "harvestAmount": 6,
      "isResource": false,
      "isStockpile": false,
      "canHarvest": true,
      "canMove": true,
      "canAttack": true,
      "produces": [],
      "producedBy": [
        "Base"
      ]
    },
    {
      "ID": 4,
      "name": "Light",
      "cost": 13,
      "produceTime": 4,
      "hp": 37,
      "minDamage": 8,
      "maxDamage": 10,
      "attackRange": 2,
      "attackTime": 2,
      "moveTime": 4,
      "sightRadius": 6,
      "harvestTime": 0,
      "returnTime": 0,
      "harvestAmount": 0,
      "isResource": false,
      "isStockpile": false,
      "canHarvest": false,
      "canMove": true,
      "canAttack": true,
      "produces": [],
      "producedBy": [
        "Barracks"
      ]
    },
    {
      "ID": 5,
      "name": "Heavy",
      "cost": 24,
      "produceTime": 6,
      "hp": 47,
      "minDamage": 28,
      "maxDamage": 11,
      "attackRange": 3,
      "attackTime": 3,
      "moveTime": 6,
      "sightRadius": 5,
      "harvestTime": 0,
      "returnTime": 0,
      "harvestAmount": 0,
      "isResource": false,
      "isStockpile": false,
      "canHarvest": false,
      "canMove": true,
      "canAttack": true,
      "produces": [],
      "producedBy": [
        "Barracks"
      ]
    },
    {
      "ID": 6,
      "name": "Ranged",
      "cost": 20,
      "produceTime": 5,
      "hp": 27,
      "minDamage": 17,
      "maxDamage": 14,
      "attackRange": 2,
      "attackTime": 2,
      "moveTime": 2,
      "sightRadius": 8,
      "harvestTime": 0,
      "returnTime": 0,
      "harvestAmount": 0,
      "isResource": false,
      "isStockpile": false,
      "canHarvest": false,
      "canMove": true,
      "canAttack": true,
      "produces": [],
      "producedBy": [
        "Barracks"
      ]
    },
    {
      "ID": 1,
      "name": "Base",
      "cost": 91,
      "produceTime": 21,
      "hp": 168,
      "minDamage": 0,
      "maxDamage": 0,
      "attackRange": 0,
      "attackTime": 0,
      "moveTime": 0,
      "sightRadius": 8,
      "harvestTime": 0,
      "returnTime": 0,
      "harvestAmount": 0,
      "isResource": false,
      "isStockpile": true,
      "canHarvest": false,
      "canMove": false,
      "canAttack": false,
      "produces": [
        "Worker"
      ],
      "producedBy": [
        "Worker"
      ]
    },
    {
      "ID": 2,
      "name": "Barracks",
      "cost": 30,
      "produceTime": 15,
      "hp": 89,
      "minDamage": 0,
      "maxDamage": 0,
      "attackRange": 0,
      "attackTime": 0,
      "moveTime": 0,
      "sightRadius": 4,
      "harvestTime": 0,
      "returnTime": 0,
      "harvestAmount": 0,
      "isResource": false,
      "isStockpile": false,
      "canHarvest": false,
      "canMove": false,
      "canAttack": false,
      "produces": [
        "Light",
        "Heavy",
        "Ranged"
      ],
      "producedBy": [
        "Worker"
      ]
    }
  ]
}